django_macaddress-1.9.0.dist-info/licenses/LICENSE
macaddress/__init__.py
macaddress/fields.py
macaddress/formfields.py
macaddress/models.py
macaddress/tests/__init__.py
macaddress/tests/models.py
macaddress/tests/test_fields.py
django_macaddress-1.9.0.dist-info/METADATA
django_macaddress-1.9.0.dist-info/WHEEL
django_macaddress-1.9.0.dist-info/top_level.txt
django_macaddress-1.9.0.dist-info/RECORD
